trust_sign/__init__.py
trust_sign/audit_trail.py
trust_sign/payment.py
trust_sign/token_sign.py
trust_sign/unit_test.py
trust_sign/utills.py
trust_sign-0.1.dist-info/METADATA
trust_sign-0.1.dist-info/WHEEL
trust_sign-0.1.dist-info/top_level.txt
trust_sign-0.1.dist-info/RECORD
