Metadata-Version: 2.1
Name: trust_sign
Version: 0.1
Summary: A library for data tokenization and detokenization
Home-page: https://github.com/Mouhawos/Trust-Sign
Author: Spidercrypt
Author-email: spidercrypt.dev@gmail.com
License: MIT
Classifier: Development Status :: 3 - Alpha
Classifier: Intended Audience :: Developers
Classifier: License :: OSI Approved :: MIT License
Classifier: Programming Language :: Python :: 3
Requires-Dist: Flask
Requires-Dist: requests
Requires-Dist: jsonify
